LICENSE
MANIFEST.in
README.md
setup.py
uxapi/__init__.py
uxapi/__version__.py
uxapi/awaitables.py
uxapi/event.py
uxapi/helpers.py
uxapi/listiter.py
uxapi/patch.py
uxapi/pipeline.py
uxapi/queue.py
uxapi/session.py
uxapi/symbol.py
uxapi/topic.py
uxapi/wshandler.py
uxapi.egg-info/PKG-INFO
uxapi.egg-info/SOURCES.txt
uxapi.egg-info/dependency_links.txt
uxapi.egg-info/requires.txt
uxapi.egg-info/top_level.txt
uxapi/exchanges/__init__.py
uxapi/exchanges/binance.py
uxapi/exchanges/bitmex.py
uxapi/exchanges/deribit.py
uxapi/exchanges/huobi.py
uxapi/exchanges/okex.py
uxapi/exchanges/ccxt/__init__.py
uxapi/exchanges/ccxt/binance.py
uxapi/exchanges/ccxt/huobidm.py
uxapi/exchanges/ccxt/okex.py