Metadata-Version: 2.1
Name: uxapi
Version: 1.0.81
Summary: Unified eXchange API
Home-page: https://github.com/lattesir/uxapi
Author: lattesir
Author-email: lattesir@163.com
License: MIT
Platform: UNKNOWN
Classifier: License :: OSI Approved :: MIT License
Classifier: Programming Language :: Python
Classifier: Programming Language :: Python :: 3
Classifier: Programming Language :: Python :: 3.7
Classifier: Programming Language :: Python :: Implementation :: CPython
Requires-Python: >=3.7.0
License-File: LICENSE
